{
  "$schema": "https://schema.management.azure.com/schemas/2015-01-01/deploymentParameters.json#",
  "contentVersion": "1.0.0.0",
  "parameters": {
    "logicAppName": {
      "value": "la-eu2-d365cssp-portalreg-sbx"
    },
    "logicAppLocation": {
      "value": "eastus2"
    },
    "Tag_AppTaxonomy": {
      "value": "Portal / CRM / Application / Sandbox"
    },
    "Tag_MaintenanceWindow": {
      "value": "Window 1"
    },
    "Tag_Realm": {
      "value": "Sandbox"
    },
    "Tag_ServiceTier": {
      "value": "Bronze"
    },
    "resource_Group_Name": {
      "value": "rg-eu2-eapidomain-customer-sbx"
    },
    "diagnosticSettings_settingName": {
      "value": "service"
    },
    "diagnosticSettings_workspaceName": {
      "value": "law-eu2-eapi-infra-sbx"
    },
    "diagnosticSettings_resourceGroupName": {
      "value": "rg-eu2-eapi-infra-sbx"
    },
    //Metrics parameters
    "alertSeverity": {
      "value": 3
    },
    "alertIsEnabled": {
      "value": true
    },
    "connections_crm_name": {
      "value": "commondataservice"
    },
    "ceDisplayname": {
      "value": "CSSP_CE_SBX from ARM"
    },
    "ceClientId": {
      "value": "f7eb0d60-64b5-4411-94ba-79d2f50e0300"
    },
    "extensionAccountField": {
      "value": "extension_b762383897f44875bdcb35317be6a660_AccountNumber"
    },
    "ceClientSecret": {
      "value": "VHz7Q~6nfALMyqcatboK~e2BUNS0AZUJ9fCZJ"
      //"reference": {
      //  "keyVault": {
      //    "id": "/subscriptions/cbab6663-d76a-47c9-ae1a-369e21f35645/resourceGroups/rg-eu2-eapidomain-customer-dev/providers/Microsoft.KeyVault/vaults/kveu2eapidcstmrdev"
      //  },
      //  "secretName": "DCE-ClientSecret"
      //}
    },
    "crm_environmentURL": { "value": "https://secusprtsbx.crm.dynamics.com/" },
    "tenantId": { "value": "b81812e7-dfea-42ed-872e-ed8cf3b20e9f" }
  }
}
